intention/__init__.py
intention/application_mode.py
intention/application_run_result.py
intention/application_state.py
intention/cli/__init__.py
intention/cli/serve.py
intention/cli_foundation/__init__.py
intention/cli_foundation/command.py
intention/cli_foundation/command_option.py
intention/dependency_injection_container.py
intention/http/__init__.py
intention/http/exception_responder.py
intention/http/exception_response.py
intention/http/jinja_response.py
intention/http/not_found_responder.py
intention/http/not_found_response.py
intention/http/recursive_responder_aggregate.py
intention/http/responder.py
intention/http/responder_caller.py
intention/http/response_interceptor.py
intention/http/response_interceptor_aggregate.py
intention/http/response_interceptor_jinja.py
intention/http/route.py
intention/http/route_match.py
intention/http/route_node.py
intention/http/router.py
intention/http/text_response.py
intention/http_foundation/__init__.py
intention/http_foundation/renderable_response.py
intention/http_foundation/request.py
intention/http_foundation/response.py
intention/import_all_from.py
intention/meta/__init__.py
intention/meta/argument_matching_function_caller.py
intention/meta/async_responder_protocol.py
intention/meta/class_property_info.py
intention/meta/function_parameter_store.py
intention/meta/get_class_properties.py
intention/meta/get_full_class_name.py
intention/meta/get_root_class.py
intention/meta/is_responder.py
intention/meta/responder_protocol.py
intention/meta/test_argument_matching_function_caller.py
intention/py.typed
intention/role/__init__.py
intention/role/intercepts_http_response.py
intention/role/responds_to_cli.py
intention/role/responds_to_http.py
intention/role/role.py
intention/role/role_registry.py
intention/role/role_regsitry_global.py
intention/role/service.py
intention/role/service_override_behavior.py
intention/role/service_provider.py
intention/rsgi/__init__.py
intention/rsgi/http_scope_responder.py
intention-0.2.1.dist-info/LICENSE.md
intention-0.2.1.dist-info/METADATA
intention-0.2.1.dist-info/WHEEL
intention-0.2.1.dist-info/RECORD
